coloreg.py
coloreg-0.6.0.dist-info/LICENSE
coloreg-0.6.0.dist-info/METADATA
coloreg-0.6.0.dist-info/WHEEL
coloreg-0.6.0.dist-info/top_level.txt
coloreg-0.6.0.dist-info/RECORD
