Metadata-Version: 2.1
Name: coloreg
Version: 0.6.0
Summary: Style, sheet, theme - simple coloring for python standard `logging` module
Home-page: https://github.com/istot/coloreg
Author: Jacek Apanasik
Author-email: jacek.apanasik@gmail.com
License: MIT License
Platform: UNKNOWN
Classifier: Development Status :: 4 - Beta
Classifier: Natural Language :: English
Classifier: License :: OSI Approved :: MIT License
Classifier: Programming Language :: Python
Classifier: Programming Language :: Python :: 3
Classifier: Programming Language :: Python :: 3.6
Classifier: Programming Language :: Python :: 3.7
Classifier: Programming Language :: Python :: 3.8
Classifier: Programming Language :: Python :: 3.9
Requires-Dist: colorama
